minimd/__init__.py
minimd/__main__.py
minimd/tokenizer.py
minimd/utils.py
minimd-1.0.2.dist-info/METADATA
minimd-1.0.2.dist-info/WHEEL
minimd-1.0.2.dist-info/entry_points.txt
minimd-1.0.2.dist-info/top_level.txt
minimd-1.0.2.dist-info/RECORD
