Metadata-Version: 2.1
Name: minimd
Version: 1.0.2
Summary: Minimal markdown parser
Author-email: entwanne <antoine.rozo@gmail.com>
License: MIT License
Project-URL: homepage, https://github.com/entwanne/minimd
Classifier: Development Status :: 5 - Production/Stable
Classifier: Programming Language :: Python :: 3
Classifier: License :: OSI Approved :: MIT License
Provides-Extra: dev
Requires-Dist: pytest ; extra == 'dev'
Requires-Dist: pytest-mock ; extra == 'dev'
Requires-Dist: flake8 ; extra == 'dev'
Requires-Dist: isort ; extra == 'dev'
